{"idGame":118092,"result":"1/2-1/2","nmEvent":"World Championship 16th","nmSite":"NLD","date":"1935.??.??","round":"5","nmWhitePlayer":"Alekhine, Alexander","nmBlackPlayer":"Euwe, Max","vlWhiteElo":"","vlBlackElo":"","cdEco":"C15","moves":[{"idMove":0,"dsMovement":"e4 e6"},{"idMove":1,"dsMovement":"d4 d5"},{"idMove":2,"dsMovement":"Nc3 Bb4"},{"idMove":3,"dsMovement":"Ne2 dxe4"},{"idMove":4,"dsMovement":"a3 Be7"},{"idMove":5,"dsMovement":"Nxe4 Nc6"},{"idMove":6,"dsMovement":"Be3 Nf6"},{"idMove":7,"dsMovement":"N2c3 O-O"},{"idMove":8,"dsMovement":"Ng3 b6"},{"idMove":9,"dsMovement":"Be2 Bb7"},{"idMove":10,"dsMovement":"O-O Qd7"},{"idMove":11,"dsMovement":"Qd2 Rad8"},{"idMove":12,"dsMovement":"Rfd1 Qc8"},{"idMove":13,"dsMovement":"Qe1 e5"},{"idMove":14,"dsMovement":"d5 Nd4"},{"idMove":15,"dsMovement":"Bxd4 exd4"},{"idMove":16,"dsMovement":"Rxd4 c5"},{"idMove":17,"dsMovement":"Ra4 Nxd5"},{"idMove":18,"dsMovement":"Bg4 Qc7"},{"idMove":19,"dsMovement":"Rxa7 Nxc3"},{"idMove":20,"dsMovement":"bxc3 Ra8"},{"idMove":21,"dsMovement":"Rxb7 Qxb7"},{"idMove":22,"dsMovement":"Bf3 Qd7"},{"idMove":23,"dsMovement":"Bxa8 Rxa8"},{"idMove":24,"dsMovement":"Qe4 Ra4"},{"idMove":25,"dsMovement":"Qe2 Bf8"},{"idMove":26,"dsMovement":"h3 Qe6"},{"idMove":27,"dsMovement":"Qxe6 fxe6"},{"idMove":28,"dsMovement":"Rb1 Rxa3"},{"idMove":29,"dsMovement":"Ne4 Ra6"},{"idMove":30,"dsMovement":"Kf1 Be7"},{"idMove":31,"dsMovement":"Ke2 Kf8"},{"idMove":32,"dsMovement":"Ke3 Bd8"},{"idMove":33,"dsMovement":"Rd1 Ke7"}]}