{"idGame":134659,"result":"1-0","nmEvent":"Leningrad","nmSite":"Leningrad","date":"1989.??.??","round":"?","nmWhitePlayer":"Vera, Reynaldo","nmBlackPlayer":"Khalifman, Alexander","vlWhiteElo":"2470","vlBlackElo":"2545","cdEco":"E94","moves":[{"idMove":0,"dsMovement":"d4 Nf6"},{"idMove":1,"dsMovement":"c4 g6"},{"idMove":2,"dsMovement":"Nc3 Bg7"},{"idMove":3,"dsMovement":"e4 d6"},{"idMove":4,"dsMovement":"Be2 O-O"},{"idMove":5,"dsMovement":"Nf3 e5"},{"idMove":6,"dsMovement":"O-O Na6"},{"idMove":7,"dsMovement":"Re1 c6"},{"idMove":8,"dsMovement":"Bf1 Bg4"},{"idMove":9,"dsMovement":"Be3 Nd7"},{"idMove":10,"dsMovement":"d5 c5"},{"idMove":11,"dsMovement":"Be2 Bxf3"},{"idMove":12,"dsMovement":"Bxf3 f5"},{"idMove":13,"dsMovement":"a3 Nf6"},{"idMove":14,"dsMovement":"g3 Ne8"},{"idMove":15,"dsMovement":"Rb1 Bf6"},{"idMove":16,"dsMovement":"Bg2 Bg5"},{"idMove":17,"dsMovement":"Bxg5 Qxg5"},{"idMove":18,"dsMovement":"exf5 gxf5"},{"idMove":19,"dsMovement":"f4 exf4"},{"idMove":20,"dsMovement":"Qd2 Qg4"},{"idMove":21,"dsMovement":"Qxf4 Qxf4"},{"idMove":22,"dsMovement":"gxf4 Rf7"},{"idMove":23,"dsMovement":"Bh3 Ng7"},{"idMove":24,"dsMovement":"Kf2 b6"},{"idMove":25,"dsMovement":"Nb5 Rd8"},{"idMove":26,"dsMovement":"b4 Kf8"},{"idMove":27,"dsMovement":"Rb3 Rdd7"},{"idMove":28,"dsMovement":"Re6 cxb4"},{"idMove":29,"dsMovement":"axb4 Nc7"},{"idMove":30,"dsMovement":"Nd4 b5"},{"idMove":31,"dsMovement":"Bf1 Rde7"},{"idMove":32,"dsMovement":"Ree3 Rxe3"},{"idMove":33,"dsMovement":"Rxe3 bxc4"},{"idMove":34,"dsMovement":"Bxc4 Nh5"},{"idMove":35,"dsMovement":"Ra3 Nxf4"},{"idMove":36,"dsMovement":"Rxa7 Ncxd5"},{"idMove":37,"dsMovement":"Ra5 Rb7"},{"idMove":38,"dsMovement":"Bxd5 Rxb4"},{"idMove":39,"dsMovement":"Ra8 Kg7"},{"idMove":40,"dsMovement":"Nxf5 Kg6"},{"idMove":41,"dsMovement":"Ne3 Rb2"},{"idMove":42,"dsMovement":"Kg3 Nh5"},{"idMove":43,"dsMovement":"Kf3 Rxh2"},{"idMove":44,"dsMovement":"Be4 Kf7"},{"idMove":45,"dsMovement":"Ra7 Kf8"},{"idMove":46,"dsMovement":"Bd5 Rh3"},{"idMove":47,"dsMovement":"Kf2 Rh2"},{"idMove":48,"dsMovement":"Ng2 h6"},{"idMove":49,"dsMovement":"Rf7 Ke8"},{"idMove":50,"dsMovement":"Rf3 Rh1"},{"idMove":51,"dsMovement":"Nf4 Kd8"},{"idMove":52,"dsMovement":"Ra3 Rh2"},{"idMove":53,"dsMovement":"Ng2 Nf6"},{"idMove":54,"dsMovement":"Bf3 d5"},{"idMove":55,"dsMovement":"Ra7 Rh1"},{"idMove":56,"dsMovement":"Nf4 Rb1"},{"idMove":57,"dsMovement":"Rf7 Ne4"},{"idMove":58,"dsMovement":"Ke3 Ng5"},{"idMove":59,"dsMovement":"Rf8 Ke7"},{"idMove":60,"dsMovement":"Ng6 Kd6"},{"idMove":61,"dsMovement":"Be2 Rg1"},{"idMove":62,"dsMovement":"Rf6 Kc5"},{"idMove":63,"dsMovement":"Ne7 d4"},{"idMove":64,"dsMovement":"Kf4 Kb4"},{"idMove":65,"dsMovement":"Nd5 Kc5"},{"idMove":66,"dsMovement":"Ne7 Kb4"},{"idMove":67,"dsMovement":"Nd5 Kc5"},{"idMove":68,"dsMovement":"Nc7 Rg2"},{"idMove":69,"dsMovement":"Na6 Kd5"},{"idMove":70,"dsMovement":"Nb4 Kc5"},{"idMove":71,"dsMovement":"Na6 Kd5"},{"idMove":72,"dsMovement":"Nb4 Kc5"},{"idMove":73,"dsMovement":"Nd3 Kc4"},{"idMove":74,"dsMovement":"Rc6 Kb5"},{"idMove":75,"dsMovement":"Rc2 Kb6"},{"idMove":76,"dsMovement":"Rb2 Kc7"},{"idMove":77,"dsMovement":"Ke5 Nh3"},{"idMove":78,"dsMovement":"Nc5 Rg5"},{"idMove":79,"dsMovement":"Kxd4 Nf4"},{"idMove":80,"dsMovement":"Rb7 Kd8"},{"idMove":81,"dsMovement":"Bc4 Rg1"},{"idMove":82,"dsMovement":"Ke5 Rd1"},{"idMove":83,"dsMovement":"Rg7 Ke8"},{"idMove":84,"dsMovement":"Bb3 Nd3"},{"idMove":85,"dsMovement":"Kd6"}]}