{"idGame":149136,"result":"1/2-1/2","nmEvent":"1st Yerevan Open 2016","nmSite":"Yerevan ARM","date":"2016.10.05","round":"4.8","nmWhitePlayer":"Petrosian,DG","nmBlackPlayer":"Tiviakov,S","vlWhiteElo":"2393","vlBlackElo":"2590","cdEco":"B01","moves":[{"idMove":0,"dsMovement":"e4 d5"},{"idMove":1,"dsMovement":"exd5 Qxd5"},{"idMove":2,"dsMovement":"Nc3 Qd6"},{"idMove":3,"dsMovement":"d4 Nf6"},{"idMove":4,"dsMovement":"Nf3 c6"},{"idMove":5,"dsMovement":"Ne5 Be6"},{"idMove":6,"dsMovement":"Bf4 Qd8"},{"idMove":7,"dsMovement":"Qf3 Qxd4"},{"idMove":8,"dsMovement":"Bd3 Nbd7"},{"idMove":9,"dsMovement":"Nxc6 bxc6"},{"idMove":10,"dsMovement":"Nb5 Bd5"},{"idMove":11,"dsMovement":"Nxd4 Bxf3"},{"idMove":12,"dsMovement":"Nxf3 e6"},{"idMove":13,"dsMovement":"O-O-O Nd5"},{"idMove":14,"dsMovement":"Bg3 Nc5"},{"idMove":15,"dsMovement":"Ne5 Nxd3"},{"idMove":16,"dsMovement":"Rxd3 Rc8"},{"idMove":17,"dsMovement":"c4 Nb6"},{"idMove":18,"dsMovement":"Rhd1 Be7"},{"idMove":19,"dsMovement":"b3 f6"},{"idMove":20,"dsMovement":"Nd7 Nd5"},{"idMove":21,"dsMovement":"Nb8 Nb4"},{"idMove":22,"dsMovement":"Rd7 e5"},{"idMove":23,"dsMovement":"Rb7 Nxa2"},{"idMove":24,"dsMovement":"Kb2 Nb4"},{"idMove":25,"dsMovement":"Rdd7 Bf8"},{"idMove":26,"dsMovement":"Rdc7 Kd8"},{"idMove":27,"dsMovement":"Rd7 Ke8"},{"idMove":28,"dsMovement":"Rdc7 Kd8"},{"idMove":29,"dsMovement":"Rd7"}]}