{"idGame":164324,"result":"1-0","nmEvent":"Vikings GM","nmSite":"York ENG","date":"1999.12.19","round":"7","nmWhitePlayer":"Sutovsky,E","nmBlackPlayer":"Hector,J","vlWhiteElo":"2587","vlBlackElo":"2505","cdEco":"C68","moves":[{"idMove":0,"dsMovement":"e4 e5"},{"idMove":1,"dsMovement":"Nf3 Nc6"},{"idMove":2,"dsMovement":"Bb5 a6"},{"idMove":3,"dsMovement":"Bxc6 dxc6"},{"idMove":4,"dsMovement":"Nc3 Qd6"},{"idMove":5,"dsMovement":"d4 exd4"},{"idMove":6,"dsMovement":"Nxd4 Bd7"},{"idMove":7,"dsMovement":"Be3 O-O-O"},{"idMove":8,"dsMovement":"Qe2 Qg6"},{"idMove":9,"dsMovement":"O-O-O Bb4"},{"idMove":10,"dsMovement":"Qc4 Bd6"},{"idMove":11,"dsMovement":"Nb3 Nh6"},{"idMove":12,"dsMovement":"Qd4 b6"},{"idMove":13,"dsMovement":"Na4 Bg4"},{"idMove":14,"dsMovement":"Nxb6 cxb6"},{"idMove":15,"dsMovement":"Qxb6 Bxd1"},{"idMove":16,"dsMovement":"Rxd1 Ng4"},{"idMove":17,"dsMovement":"Qxa6 Kd7"},{"idMove":18,"dsMovement":"Bf4 Ke7"},{"idMove":19,"dsMovement":"Bxd6 Rxd6"},{"idMove":20,"dsMovement":"Qb7 Ke6"},{"idMove":21,"dsMovement":"Nc5 Ke5"},{"idMove":22,"dsMovement":"Qe7 Re6"},{"idMove":23,"dsMovement":"Qc7"}]}