{"idGame":17855,"result":"0-1","nmEvent":"USA-ch","nmSite":"Berkeley","date":"1984.??.??","round":"7","nmWhitePlayer":"Byrne, Robert E","nmBlackPlayer":"Alburt, Lev O","vlWhiteElo":"2510","vlBlackElo":"2455","cdEco":"B03","moves":[{"idMove":0,"dsMovement":"e4 Nf6"},{"idMove":1,"dsMovement":"e5 Nd5"},{"idMove":2,"dsMovement":"d4 d6"},{"idMove":3,"dsMovement":"c4 Nb6"},{"idMove":4,"dsMovement":"f4 dxe5"},{"idMove":5,"dsMovement":"fxe5 Nc6"},{"idMove":6,"dsMovement":"Be3 Bf5"},{"idMove":7,"dsMovement":"Nc3 e6"},{"idMove":8,"dsMovement":"Nf3 Bg4"},{"idMove":9,"dsMovement":"Be2 Bxf3"},{"idMove":10,"dsMovement":"gxf3 Qh4"},{"idMove":11,"dsMovement":"Bf2 Qf4"},{"idMove":12,"dsMovement":"c5 Nd7"},{"idMove":13,"dsMovement":"Qc1 Qxc1"},{"idMove":14,"dsMovement":"Rxc1 O-O-O"},{"idMove":15,"dsMovement":"Ne4 Ndb8"},{"idMove":16,"dsMovement":"Ng5 Rd7"},{"idMove":17,"dsMovement":"Bb5 h6"},{"idMove":18,"dsMovement":"Ne4 g6"},{"idMove":19,"dsMovement":"O-O Bg7"},{"idMove":20,"dsMovement":"f4 h5"},{"idMove":21,"dsMovement":"Rc4 Bh6"},{"idMove":22,"dsMovement":"Be3 a6"},{"idMove":23,"dsMovement":"Ba4 Rdd8"},{"idMove":24,"dsMovement":"b4 Na7"},{"idMove":25,"dsMovement":"Bb3 Nbc6"},{"idMove":26,"dsMovement":"a4 Kb8"},{"idMove":27,"dsMovement":"Kg2 Ne7"},{"idMove":28,"dsMovement":"Kf3 Nd5"},{"idMove":29,"dsMovement":"Bd2 b5"},{"idMove":30,"dsMovement":"cxb6 Nxb6"},{"idMove":31,"dsMovement":"Rc2 Rxd4"},{"idMove":32,"dsMovement":"Nc5 Ka8"},{"idMove":33,"dsMovement":"Ke3 Rhd8"},{"idMove":34,"dsMovement":"a5 Nb5"},{"idMove":35,"dsMovement":"axb6 cxb6"},{"idMove":36,"dsMovement":"Nxe6 fxe6"},{"idMove":37,"dsMovement":"Bxe6 g5"},{"idMove":38,"dsMovement":"Be1 gxf4"},{"idMove":39,"dsMovement":"Kf3 Rd3"},{"idMove":40,"dsMovement":"Kg2 f3"},{"idMove":41,"dsMovement":"Kg3 Bg7"},{"idMove":42,"dsMovement":"Kh4 Bxe5"},{"idMove":43,"dsMovement":"Kxh5 Ka7"},{"idMove":44,"dsMovement":"Bc4 R3d7"},{"idMove":45,"dsMovement":"Bxb5 Rg7"},{"idMove":46,"dsMovement":"Bd2 Rh8"},{"idMove":47,"dsMovement":"Bh6 Bf4"},{"idMove":48,"dsMovement":"Rc6 Rg5"},{"idMove":49,"dsMovement":"Kh4"}]}