{"idGame":21015,"result":"1-0","nmEvent":"Rubinstein mem","nmSite":"Polanica Zdroj","date":"1967.??.??","round":"5","nmWhitePlayer":"Hort, Vlastimil","nmBlackPlayer":"Kolarov, Atanas S","vlWhiteElo":"","vlBlackElo":"","cdEco":"C68","moves":[{"idMove":0,"dsMovement":"e4 e5"},{"idMove":1,"dsMovement":"Nf3 Nc6"},{"idMove":2,"dsMovement":"Bb5 a6"},{"idMove":3,"dsMovement":"Bxc6 dxc6"},{"idMove":4,"dsMovement":"O-O Bg4"},{"idMove":5,"dsMovement":"h3 Bxf3"},{"idMove":6,"dsMovement":"Qxf3 Qf6"},{"idMove":7,"dsMovement":"Qg3 Bd6"},{"idMove":8,"dsMovement":"d3 Qg6"},{"idMove":9,"dsMovement":"Be3 Qxg3"},{"idMove":10,"dsMovement":"fxg3 Ne7"},{"idMove":11,"dsMovement":"Nd2 c5"},{"idMove":12,"dsMovement":"Rf3 Nc6"},{"idMove":13,"dsMovement":"c3 Rd8"},{"idMove":14,"dsMovement":"Kf2 O-O"},{"idMove":15,"dsMovement":"Ke2 Rd7"},{"idMove":16,"dsMovement":"Raf1 b6"},{"idMove":17,"dsMovement":"g4 Rfd8"},{"idMove":18,"dsMovement":"h4 Bf8"},{"idMove":19,"dsMovement":"g5 Rxd3"},{"idMove":20,"dsMovement":"Rxf7 R3d7"},{"idMove":21,"dsMovement":"R7f5 g6"},{"idMove":22,"dsMovement":"Rf6 Na5"},{"idMove":23,"dsMovement":"h5 Bg7"},{"idMove":24,"dsMovement":"R6f3 Nb7"},{"idMove":25,"dsMovement":"h6 Bf8"},{"idMove":26,"dsMovement":"Nc4 Bd6"},{"idMove":27,"dsMovement":"Bc1 Re7"},{"idMove":28,"dsMovement":"Ne3 c6"},{"idMove":29,"dsMovement":"Ng4 Rc7"},{"idMove":30,"dsMovement":"c4 Rf8"},{"idMove":31,"dsMovement":"Rxf8 Bxf8"},{"idMove":32,"dsMovement":"Nf6 Kh8"},{"idMove":33,"dsMovement":"Ne8"}]}