{"idGame":219613,"result":"1/2-1/2","nmEvent":"ch-CHN 2011","nmSite":"Xinghua Jiangsu CHN","date":"2011.04.07","round":"8","nmWhitePlayer":"Hou Yifan","nmBlackPlayer":"Ding,L","vlWhiteElo":"2602","vlBlackElo":"2637","cdEco":"C11","moves":[{"idMove":0,"dsMovement":"e4 e6"},{"idMove":1,"dsMovement":"d4 d5"},{"idMove":2,"dsMovement":"Nc3 Nf6"},{"idMove":3,"dsMovement":"Bg5 dxe4"},{"idMove":4,"dsMovement":"Nxe4 Nbd7"},{"idMove":5,"dsMovement":"Nf3 h6"},{"idMove":6,"dsMovement":"Nxf6 Nxf6"},{"idMove":7,"dsMovement":"Bh4 c5"},{"idMove":8,"dsMovement":"Bc4 a6"},{"idMove":9,"dsMovement":"O-O Be7"},{"idMove":10,"dsMovement":"Bb3 O-O"},{"idMove":11,"dsMovement":"Qe2 cxd4"},{"idMove":12,"dsMovement":"Rad1 Nd7"},{"idMove":13,"dsMovement":"Bxe7 Qxe7"},{"idMove":14,"dsMovement":"Rxd4 Nc5"},{"idMove":15,"dsMovement":"Ne5 Bd7"},{"idMove":16,"dsMovement":"Nxd7 Nxd7"},{"idMove":17,"dsMovement":"c3 Rfd8"},{"idMove":18,"dsMovement":"Rfd1 Nf6"},{"idMove":19,"dsMovement":"Qd3 Rxd4"},{"idMove":20,"dsMovement":"Qxd4 Rc8"},{"idMove":21,"dsMovement":"f3 Qc7"},{"idMove":22,"dsMovement":"Qd6 Qxd6"},{"idMove":23,"dsMovement":"Rxd6 Kf8"},{"idMove":24,"dsMovement":"Kf2 Ke7"},{"idMove":25,"dsMovement":"Rd4 Ne8"},{"idMove":26,"dsMovement":"h4 h5"},{"idMove":27,"dsMovement":"Rc4 Rd8"},{"idMove":28,"dsMovement":"Ke2 g6"},{"idMove":29,"dsMovement":"Bc2 Rd7"}]}