{"idGame":221468,"result":"1-0","nmEvent":"Kasparov Simul Pula 2015","nmSite":"Pula CRO","date":"2015.08.19","round":"1.2","nmWhitePlayer":"Kasparov,G","nmBlackPlayer":"Pahljina,Marko","vlWhiteElo":"2812","vlBlackElo":"1737","cdEco":"B00","moves":[{"idMove":0,"dsMovement":"e4 d6"},{"idMove":1,"dsMovement":"d4 Nf6"},{"idMove":2,"dsMovement":"f3 Nbd7"},{"idMove":3,"dsMovement":"Be3 e5"},{"idMove":4,"dsMovement":"d5 Be7"},{"idMove":5,"dsMovement":"Qd2 O-O"},{"idMove":6,"dsMovement":"c4 a5"},{"idMove":7,"dsMovement":"Ne2 b6"},{"idMove":8,"dsMovement":"Nbc3 Nc5"},{"idMove":9,"dsMovement":"Ng3 h6"},{"idMove":10,"dsMovement":"Bd3 Nxd3"},{"idMove":11,"dsMovement":"Qxd3 Ne8"},{"idMove":12,"dsMovement":"Nf5 Bxf5"},{"idMove":13,"dsMovement":"exf5 Bg5"},{"idMove":14,"dsMovement":"Bf2 Qd7"},{"idMove":15,"dsMovement":"h4 Be7"},{"idMove":16,"dsMovement":"O-O-O Rb8"},{"idMove":17,"dsMovement":"g4 c6"},{"idMove":18,"dsMovement":"Kb1 Nc7"},{"idMove":19,"dsMovement":"g5 hxg5"},{"idMove":20,"dsMovement":"hxg5 Bxg5"},{"idMove":21,"dsMovement":"dxc6 Qxc6"},{"idMove":22,"dsMovement":"f4 Bxf4"},{"idMove":23,"dsMovement":"f6 Bh6"},{"idMove":24,"dsMovement":"Rxh6 e4"},{"idMove":25,"dsMovement":"Rdh1 gxh6"},{"idMove":26,"dsMovement":"Qg3"}]}