{"idGame":25618,"result":"0-1","nmEvent":"Canada zt","nmSite":"Canada","date":"1986.??.??","round":"?","nmWhitePlayer":"Nickoloff, Bryon","nmBlackPlayer":"Ivanov, Igor V","vlWhiteElo":"2420","vlBlackElo":"2495","cdEco":"E94","moves":[{"idMove":0,"dsMovement":"d4 Nf6"},{"idMove":1,"dsMovement":"c4 g6"},{"idMove":2,"dsMovement":"Nc3 Bg7"},{"idMove":3,"dsMovement":"e4 d6"},{"idMove":4,"dsMovement":"Nf3 O-O"},{"idMove":5,"dsMovement":"Be2 e5"},{"idMove":6,"dsMovement":"Be3 Nbd7"},{"idMove":7,"dsMovement":"O-O Re8"},{"idMove":8,"dsMovement":"d5 Ng4"},{"idMove":9,"dsMovement":"Bg5 f6"},{"idMove":10,"dsMovement":"Bh4 Nh6"},{"idMove":11,"dsMovement":"Nd2 Nf7"},{"idMove":12,"dsMovement":"f3 Bh6"},{"idMove":13,"dsMovement":"Bf2 c6"},{"idMove":14,"dsMovement":"dxc6 bxc6"},{"idMove":15,"dsMovement":"b4 Nf8"},{"idMove":16,"dsMovement":"Nb3 Be6"},{"idMove":17,"dsMovement":"Qc2 Qc7"},{"idMove":18,"dsMovement":"Rfd1 Rab8"},{"idMove":19,"dsMovement":"a3 Red8"},{"idMove":20,"dsMovement":"c5 d5"},{"idMove":21,"dsMovement":"exd5 cxd5"},{"idMove":22,"dsMovement":"Nb5 Qe7"},{"idMove":23,"dsMovement":"c6 Rxb5"},{"idMove":24,"dsMovement":"Bxb5 d4"},{"idMove":25,"dsMovement":"Nxd4 exd4"},{"idMove":26,"dsMovement":"Rxd4 Rc8"},{"idMove":27,"dsMovement":"Bf1 Qc7"},{"idMove":28,"dsMovement":"b5 Bf4"},{"idMove":29,"dsMovement":"Ra4 Bxh2"},{"idMove":30,"dsMovement":"Kh1 Bg3"},{"idMove":31,"dsMovement":"Rxa7 Qe5"},{"idMove":32,"dsMovement":"Bxg3 Qxa1"},{"idMove":33,"dsMovement":"Qe2 Ne5"},{"idMove":34,"dsMovement":"Ra4 Bf5"},{"idMove":35,"dsMovement":"Bxe5 fxe5"},{"idMove":36,"dsMovement":"g4 Be6"},{"idMove":37,"dsMovement":"Re4 Rd8"},{"idMove":38,"dsMovement":"Rxe5 Rd1"},{"idMove":39,"dsMovement":"Rxe6 Rxf1"},{"idMove":40,"dsMovement":"Kg2 Rg1"},{"idMove":41,"dsMovement":"Kh3 Rh1"},{"idMove":42,"dsMovement":"Kg3 Qg1"},{"idMove":43,"dsMovement":"Kf4 Qc1"},{"idMove":44,"dsMovement":"Kg3 h5"},{"idMove":45,"dsMovement":"Re3 Ne6"},{"idMove":46,"dsMovement":"gxh5 Qg1"},{"idMove":47,"dsMovement":"Qg2 Rh3"}]}