{"idGame":263890,"result":"0-1","nmEvent":"World Cup","nmSite":"Barcelona","date":"1989.??.??","round":"?","nmWhitePlayer":"Kortschnoj, Viktor","nmBlackPlayer":"Huebner, Robert","vlWhiteElo":"2610","vlBlackElo":"2600","cdEco":"B26","moves":[{"idMove":0,"dsMovement":"e4 c5"},{"idMove":1,"dsMovement":"Nc3 Nc6"},{"idMove":2,"dsMovement":"Nge2 e5"},{"idMove":3,"dsMovement":"g3 d6"},{"idMove":4,"dsMovement":"Bg2 g6"},{"idMove":5,"dsMovement":"d3 Bg7"},{"idMove":6,"dsMovement":"O-O Nge7"},{"idMove":7,"dsMovement":"f4 O-O"},{"idMove":8,"dsMovement":"Be3 Nd4"},{"idMove":9,"dsMovement":"Qd2 Be6"},{"idMove":10,"dsMovement":"Rae1 Qd7"},{"idMove":11,"dsMovement":"Nc1 Rae8"},{"idMove":12,"dsMovement":"Nd1 b6"},{"idMove":13,"dsMovement":"fxe5 dxe5"},{"idMove":14,"dsMovement":"c3 Ndc6"},{"idMove":15,"dsMovement":"Bh6 c4"},{"idMove":16,"dsMovement":"dxc4 Qxd2"},{"idMove":17,"dsMovement":"Bxd2 Bxc4"},{"idMove":18,"dsMovement":"Rf2 Rd8"},{"idMove":19,"dsMovement":"Bh3 f5"},{"idMove":20,"dsMovement":"Ne3 Ba6"},{"idMove":21,"dsMovement":"Bf1 Bxf1"},{"idMove":22,"dsMovement":"Nxf1 Rd7"},{"idMove":23,"dsMovement":"Nb3 Rfd8"},{"idMove":24,"dsMovement":"Kg2 Rf8"},{"idMove":25,"dsMovement":"Bc1 Nc8"},{"idMove":26,"dsMovement":"a4 Rdf7"},{"idMove":27,"dsMovement":"Rd1 f4"},{"idMove":28,"dsMovement":"h4 h5"},{"idMove":29,"dsMovement":"Nh2 Bf6"},{"idMove":30,"dsMovement":"Nf3 fxg3"},{"idMove":31,"dsMovement":"Rff1 Kg7"},{"idMove":32,"dsMovement":"Be3 Nd8"},{"idMove":33,"dsMovement":"Nbd2 Nd6"},{"idMove":34,"dsMovement":"Kxg3 Ne6"},{"idMove":35,"dsMovement":"Ng5 Bxg5"},{"idMove":36,"dsMovement":"Rxf7 Nxf7"},{"idMove":37,"dsMovement":"hxg5 Nfxg5"},{"idMove":38,"dsMovement":"a5 Rd8"},{"idMove":39,"dsMovement":"axb6 axb6"},{"idMove":40,"dsMovement":"Re1 b5"},{"idMove":41,"dsMovement":"c4 bxc4"},{"idMove":42,"dsMovement":"Nxc4 Nxe4"},{"idMove":43,"dsMovement":"Kg2 Rc8"},{"idMove":44,"dsMovement":"Nxe5 Rc2"},{"idMove":45,"dsMovement":"Kf3 N4g5"},{"idMove":46,"dsMovement":"Kg3 Rxb2"},{"idMove":47,"dsMovement":"Ra1 Rb5"},{"idMove":48,"dsMovement":"Ra7 Kf6"},{"idMove":49,"dsMovement":"Nd7 Kf5"},{"idMove":50,"dsMovement":"Ra1 Ne4"},{"idMove":51,"dsMovement":"Kh4 Nd6"},{"idMove":52,"dsMovement":"Rf1 Ke4"},{"idMove":53,"dsMovement":"Rf6 Nf5"},{"idMove":54,"dsMovement":"Kh3 Kxe3"},{"idMove":55,"dsMovement":"Rxe6 Kf2"},{"idMove":56,"dsMovement":"Ne5 Rb3"},{"idMove":57,"dsMovement":"Kh2 Re3"},{"idMove":58,"dsMovement":"Rxg6 Rxe5"},{"idMove":59,"dsMovement":"Rg2 Kf3"},{"idMove":60,"dsMovement":"Rg5 h4"},{"idMove":61,"dsMovement":"Kh3 Rd5"}]}