{"idGame":272462,"result":"1-0","nmEvent":"Budapest","nmSite":"Budapest","date":"1952.??.??","round":"5","nmWhitePlayer":"Benko, Pal C","nmBlackPlayer":"Kottnauer, Cenek","vlWhiteElo":"","vlBlackElo":"","cdEco":"D77","moves":[{"idMove":0,"dsMovement":"Nf3 Nf6"},{"idMove":1,"dsMovement":"g3 g6"},{"idMove":2,"dsMovement":"Bg2 Bg7"},{"idMove":3,"dsMovement":"c4 O-O"},{"idMove":4,"dsMovement":"O-O d5"},{"idMove":5,"dsMovement":"d4 dxc4"},{"idMove":6,"dsMovement":"Na3 Nc6"},{"idMove":7,"dsMovement":"Nxc4 Be6"},{"idMove":8,"dsMovement":"b3 a5"},{"idMove":9,"dsMovement":"Bb2 Bd5"},{"idMove":10,"dsMovement":"Rc1 a4"},{"idMove":11,"dsMovement":"bxa4 Qc8"},{"idMove":12,"dsMovement":"Nfe5 Bxg2"},{"idMove":13,"dsMovement":"Kxg2 Qe6"},{"idMove":14,"dsMovement":"Qb3 Qd5"},{"idMove":15,"dsMovement":"Nf3 Bh6"},{"idMove":16,"dsMovement":"e3 Na5"},{"idMove":17,"dsMovement":"Nxa5 Qxa5"},{"idMove":18,"dsMovement":"Rc5 Qxa4"},{"idMove":19,"dsMovement":"Rxc7 Qxb3"},{"idMove":20,"dsMovement":"axb3 Ra2"},{"idMove":21,"dsMovement":"Rb1 Nd5"},{"idMove":22,"dsMovement":"Rxb7 Rc8"},{"idMove":23,"dsMovement":"Ne1 Bxe3"},{"idMove":24,"dsMovement":"fxe3 Nc3"},{"idMove":25,"dsMovement":"Rc1 Rxb2"},{"idMove":26,"dsMovement":"Kh3 Kg7"},{"idMove":27,"dsMovement":"Nd3 Re2"},{"idMove":28,"dsMovement":"Rxe7 h5"},{"idMove":29,"dsMovement":"Rf1 Nd5"},{"idMove":30,"dsMovement":"Rfxf7 Kh6"},{"idMove":31,"dsMovement":"Rh7 Kg5"},{"idMove":32,"dsMovement":"Re5 Kf6"},{"idMove":33,"dsMovement":"Nf4 Nxf4"},{"idMove":34,"dsMovement":"exf4 Rb2"},{"idMove":35,"dsMovement":"d5 Rf8"},{"idMove":36,"dsMovement":"Rhe7 Rxb3"},{"idMove":37,"dsMovement":"Kh4 Rd3"},{"idMove":38,"dsMovement":"R7e6 Kg7"},{"idMove":39,"dsMovement":"Kg5 Rd8"},{"idMove":40,"dsMovement":"Rxg6 Kf7"}]}