{"idGame":283808,"result":"1/2-1/2","nmEvent":"TCh-AUT 2009-10","nmSite":"Baden AUT","date":"2010.03.28","round":"9","nmWhitePlayer":"Buhmann,R","nmBlackPlayer":"Ribli,Z","vlWhiteElo":"2603","vlBlackElo":"2559","cdEco":"D17","moves":[{"idMove":0,"dsMovement":"Nf3 Nf6"},{"idMove":1,"dsMovement":"c4 c6"},{"idMove":2,"dsMovement":"d4 d5"},{"idMove":3,"dsMovement":"Nc3 dxc4"},{"idMove":4,"dsMovement":"a4 Bf5"},{"idMove":5,"dsMovement":"Ne5 Nbd7"},{"idMove":6,"dsMovement":"Nxc4 Qc7"},{"idMove":7,"dsMovement":"g3 e5"},{"idMove":8,"dsMovement":"dxe5 Nxe5"},{"idMove":9,"dsMovement":"Bf4 Nfd7"},{"idMove":10,"dsMovement":"Bg2 g5"},{"idMove":11,"dsMovement":"Bxe5 Nxe5"},{"idMove":12,"dsMovement":"Qd4 f6"},{"idMove":13,"dsMovement":"Ne3 Bg6"},{"idMove":14,"dsMovement":"a5 a6"},{"idMove":15,"dsMovement":"Ne4 Rd8"},{"idMove":16,"dsMovement":"Qc3 Qe7"},{"idMove":17,"dsMovement":"O-O Bxe4"},{"idMove":18,"dsMovement":"Bxe4 Qb4"},{"idMove":19,"dsMovement":"Bf5 Kf7"},{"idMove":20,"dsMovement":"Ra3 Qxc3"},{"idMove":21,"dsMovement":"Rxc3 Bb4"},{"idMove":22,"dsMovement":"Rb3 c5"},{"idMove":23,"dsMovement":"Be4 Nc6"},{"idMove":24,"dsMovement":"Bxc6 bxc6"},{"idMove":25,"dsMovement":"Nc2 Rhe8"},{"idMove":26,"dsMovement":"e3 Bxa5"},{"idMove":27,"dsMovement":"Ra1 Rd2"},{"idMove":28,"dsMovement":"Rxa5 Rxc2"},{"idMove":29,"dsMovement":"Rxa6 Rd8"},{"idMove":30,"dsMovement":"Rc3 Rxb2"},{"idMove":31,"dsMovement":"Rxc5 Rdd2"},{"idMove":32,"dsMovement":"Rf5 Rbc2"}]}