{"idGame":297923,"result":"1/2-1/2","nmEvent":"77th Tata Steel GpA","nmSite":"Wijk aan Zee NED","date":"2015.01.10","round":"1.7","nmWhitePlayer":"So,W","nmBlackPlayer":"Wojtaszek,R","vlWhiteElo":"2762","vlBlackElo":"2744","cdEco":"B90","moves":[{"idMove":0,"dsMovement":"e4 c5"},{"idMove":1,"dsMovement":"Nf3 d6"},{"idMove":2,"dsMovement":"d4 cxd4"},{"idMove":3,"dsMovement":"Nxd4 Nf6"},{"idMove":4,"dsMovement":"Nc3 a6"},{"idMove":5,"dsMovement":"Be3 e5"},{"idMove":6,"dsMovement":"Nb3 Be6"},{"idMove":7,"dsMovement":"f3 h5"},{"idMove":8,"dsMovement":"Nd5 Bxd5"},{"idMove":9,"dsMovement":"exd5 Nbd7"},{"idMove":10,"dsMovement":"Be2 g6"},{"idMove":11,"dsMovement":"Qd2 Bg7"},{"idMove":12,"dsMovement":"O-O b6"},{"idMove":13,"dsMovement":"Rae1 O-O"},{"idMove":14,"dsMovement":"c4 Rc8"},{"idMove":15,"dsMovement":"h3 Nh7"},{"idMove":16,"dsMovement":"Na1 a5"},{"idMove":17,"dsMovement":"Nc2 Bf6"},{"idMove":18,"dsMovement":"Na3 Bh4"},{"idMove":19,"dsMovement":"Rb1 f5"},{"idMove":20,"dsMovement":"Nb5 f4"},{"idMove":21,"dsMovement":"Bf2 Bxf2"},{"idMove":22,"dsMovement":"Rxf2 Nc5"},{"idMove":23,"dsMovement":"Qc2 Qf6"},{"idMove":24,"dsMovement":"b3 Ng5"},{"idMove":25,"dsMovement":"Bd3 Kg7"},{"idMove":26,"dsMovement":"a3 Nf7"},{"idMove":27,"dsMovement":"b4 Nxd3"},{"idMove":28,"dsMovement":"Qxd3 Qf5"},{"idMove":29,"dsMovement":"Qxf5 gxf5"},{"idMove":30,"dsMovement":"Rc2 Kf6"},{"idMove":31,"dsMovement":"bxa5 bxa5"},{"idMove":32,"dsMovement":"Na7 Rb8"},{"idMove":33,"dsMovement":"Rb5 a4"},{"idMove":34,"dsMovement":"Nc6 Rbc8"},{"idMove":35,"dsMovement":"c5 dxc5"},{"idMove":36,"dsMovement":"Rb6 Nd6"},{"idMove":37,"dsMovement":"Na5 Ke7"},{"idMove":38,"dsMovement":"Nc6 Kf6"},{"idMove":39,"dsMovement":"Na7 Rcd8"},{"idMove":40,"dsMovement":"Rxc5 e4"},{"idMove":41,"dsMovement":"Ra5 Rd7"},{"idMove":42,"dsMovement":"Raa6 Ke5"},{"idMove":43,"dsMovement":"Nc6 Kxd5"},{"idMove":44,"dsMovement":"Ra5 Ke6"},{"idMove":45,"dsMovement":"fxe4 fxe4"},{"idMove":46,"dsMovement":"Rxh5 Rf6"},{"idMove":47,"dsMovement":"Nd4 Ke7"},{"idMove":48,"dsMovement":"Nc6 Ke6"},{"idMove":49,"dsMovement":"Nd4 Ke7"},{"idMove":50,"dsMovement":"Re5 Kf7"},{"idMove":51,"dsMovement":"Rd5 Ke8"},{"idMove":52,"dsMovement":"Rb8 Kf7"},{"idMove":53,"dsMovement":"Nb5 Ke6"},{"idMove":54,"dsMovement":"Nc3 f3"},{"idMove":55,"dsMovement":"Rb6 Rg6"},{"idMove":56,"dsMovement":"g4 Rh6"},{"idMove":57,"dsMovement":"Kh2 f2"},{"idMove":58,"dsMovement":"Rf5 e3"},{"idMove":59,"dsMovement":"Kg2 Rc7"},{"idMove":60,"dsMovement":"Nd5 Kd7"},{"idMove":61,"dsMovement":"Re5 Rc5"},{"idMove":62,"dsMovement":"Rb1 Nc4"},{"idMove":63,"dsMovement":"Rf5 Kd6"},{"idMove":64,"dsMovement":"Rb8 Re6"},{"idMove":65,"dsMovement":"Rd8 Kc6"},{"idMove":66,"dsMovement":"Rc8 Kd6"},{"idMove":67,"dsMovement":"Rd8 Kc6"},{"idMove":68,"dsMovement":"Rc8 Kd6"},{"idMove":69,"dsMovement":"Rd8"}]}