{"idGame":340266,"result":"1-0","nmEvent":"6th Gibtelecom Masters","nmSite":"Gibraltar ENG","date":"2008.01.28","round":"7","nmWhitePlayer":"Akobian,V","nmBlackPlayer":"Shen Yang","vlWhiteElo":"2599","vlBlackElo":"2429","cdEco":"D16","moves":[{"idMove":0,"dsMovement":"d4 d5"},{"idMove":1,"dsMovement":"Nf3 Nf6"},{"idMove":2,"dsMovement":"c4 c6"},{"idMove":3,"dsMovement":"Nc3 dxc4"},{"idMove":4,"dsMovement":"a4 e6"},{"idMove":5,"dsMovement":"g3 c5"},{"idMove":6,"dsMovement":"Bg5 cxd4"},{"idMove":7,"dsMovement":"Qxd4 Qxd4"},{"idMove":8,"dsMovement":"Nxd4 Na6"},{"idMove":9,"dsMovement":"Bg2 h6"},{"idMove":10,"dsMovement":"Bf4 Bb4"},{"idMove":11,"dsMovement":"O-O Ke7"},{"idMove":12,"dsMovement":"Ndb5 g5"},{"idMove":13,"dsMovement":"Be5 Rd8"},{"idMove":14,"dsMovement":"Rfd1 Rxd1"},{"idMove":15,"dsMovement":"Rxd1 Ne8"},{"idMove":16,"dsMovement":"Bd4 Bc5"},{"idMove":17,"dsMovement":"e3 f6"},{"idMove":18,"dsMovement":"f4 Rb8"},{"idMove":19,"dsMovement":"Nxa7 Bd7"},{"idMove":20,"dsMovement":"Nab5 gxf4"},{"idMove":21,"dsMovement":"gxf4 Bc6"},{"idMove":22,"dsMovement":"Bf1 Ng7"},{"idMove":23,"dsMovement":"Bxc4 Nf5"},{"idMove":24,"dsMovement":"Kf2 Rg8"},{"idMove":25,"dsMovement":"Bf1 Nxd4"},{"idMove":26,"dsMovement":"Nxd4 Nb4"},{"idMove":27,"dsMovement":"Nxc6 bxc6"},{"idMove":28,"dsMovement":"Ne4 Bb6"},{"idMove":29,"dsMovement":"Rd7 Kxd7"},{"idMove":30,"dsMovement":"Nxf6 Kd6"},{"idMove":31,"dsMovement":"Nxg8 Nd5"},{"idMove":32,"dsMovement":"Kf3 Bxe3"},{"idMove":33,"dsMovement":"Bc4 Bd4"},{"idMove":34,"dsMovement":"Bxd5 exd5"},{"idMove":35,"dsMovement":"Nxh6 Bxb2"},{"idMove":36,"dsMovement":"Nf7 Ke6"},{"idMove":37,"dsMovement":"Ne5 c5"},{"idMove":38,"dsMovement":"a5 Kd6"},{"idMove":39,"dsMovement":"h4"}]}