{"idGame":348495,"result":"1-0","nmEvent":"UT Dallas GM Inv 2013","nmSite":"Dallas USA","date":"2013.11.22","round":"2.3","nmWhitePlayer":"Ehlvest,J","nmBlackPlayer":"Iotov,V","vlWhiteElo":"2574","vlBlackElo":"2568","cdEco":"B13","moves":[{"idMove":0,"dsMovement":"e4 c6"},{"idMove":1,"dsMovement":"d4 d5"},{"idMove":2,"dsMovement":"exd5 cxd5"},{"idMove":3,"dsMovement":"Bd3 Nc6"},{"idMove":4,"dsMovement":"c3 Qc7"},{"idMove":5,"dsMovement":"h3 e6"},{"idMove":6,"dsMovement":"Nf3 Bd6"},{"idMove":7,"dsMovement":"O-O f6"},{"idMove":8,"dsMovement":"Re1 Qf7"},{"idMove":9,"dsMovement":"c4 Nge7"},{"idMove":10,"dsMovement":"Nc3 O-O"},{"idMove":11,"dsMovement":"a3 a6"},{"idMove":12,"dsMovement":"b4 Bd7"},{"idMove":13,"dsMovement":"b5 axb5"},{"idMove":14,"dsMovement":"Nxb5 Bb8"},{"idMove":15,"dsMovement":"Rb1 dxc4"},{"idMove":16,"dsMovement":"Bxc4 Nd5"},{"idMove":17,"dsMovement":"Bd2 Rc8"},{"idMove":18,"dsMovement":"Qe2 Nce7"},{"idMove":19,"dsMovement":"Rb3 Ra4"},{"idMove":20,"dsMovement":"Bd3 h6"},{"idMove":21,"dsMovement":"Qd1 g5"},{"idMove":22,"dsMovement":"Rb1 Ra8"},{"idMove":23,"dsMovement":"a4 Ra6"},{"idMove":24,"dsMovement":"g3 Kg7"},{"idMove":25,"dsMovement":"a5 Qh5"},{"idMove":26,"dsMovement":"Bf1 Rac6"},{"idMove":27,"dsMovement":"Rb3 Rc2"},{"idMove":28,"dsMovement":"Na3 Ba4"},{"idMove":29,"dsMovement":"Rxb7 R2c7"},{"idMove":30,"dsMovement":"Qxa4 Rxb7"},{"idMove":31,"dsMovement":"Kg2 Rb2"},{"idMove":32,"dsMovement":"Nc4 Rxc4"},{"idMove":33,"dsMovement":"Bxc4 g4"},{"idMove":34,"dsMovement":"hxg4 Qxg4"},{"idMove":35,"dsMovement":"Bxd5"}]}