{"idGame":355847,"result":"1-0","nmEvent":"TCh-RUS Premier","nmSite":"Olginka RUS","date":"2011.04.13","round":"2","nmWhitePlayer":"Svidler,P","nmBlackPlayer":"Grishchenko,S1","vlWhiteElo":"2730","vlBlackElo":"2475","cdEco":"D35","moves":[{"idMove":0,"dsMovement":"c4 Nf6"},{"idMove":1,"dsMovement":"d4 e6"},{"idMove":2,"dsMovement":"Nc3 d5"},{"idMove":3,"dsMovement":"Bf4 Be7"},{"idMove":4,"dsMovement":"e3 O-O"},{"idMove":5,"dsMovement":"Rc1 a6"},{"idMove":6,"dsMovement":"c5 Nc6"},{"idMove":7,"dsMovement":"a3 b6"},{"idMove":8,"dsMovement":"b4 Bb7"},{"idMove":9,"dsMovement":"Bd3 Nd7"},{"idMove":10,"dsMovement":"Nf3 Bf6"},{"idMove":11,"dsMovement":"Bb1 bxc5"},{"idMove":12,"dsMovement":"bxc5 g6"},{"idMove":13,"dsMovement":"O-O Bg7"},{"idMove":14,"dsMovement":"Bg3 Ne7"},{"idMove":15,"dsMovement":"Qa4 h6"},{"idMove":16,"dsMovement":"Bd3 Ra7"},{"idMove":17,"dsMovement":"Na2 Nf5"},{"idMove":18,"dsMovement":"Bxf5 exf5"},{"idMove":19,"dsMovement":"Rb1 Nf6"},{"idMove":20,"dsMovement":"c6 Bc8"},{"idMove":21,"dsMovement":"Nc3 Ne4"},{"idMove":22,"dsMovement":"Nb5 Nxg3"},{"idMove":23,"dsMovement":"hxg3 Ra8"},{"idMove":24,"dsMovement":"Qa5 Be6"},{"idMove":25,"dsMovement":"Nxc7 Rc8"},{"idMove":26,"dsMovement":"Rb7 Re8"},{"idMove":27,"dsMovement":"Qb6 Re7"},{"idMove":28,"dsMovement":"Nxd5 Qxd5"},{"idMove":29,"dsMovement":"Rxe7 Rxc6"},{"idMove":30,"dsMovement":"Qb8 Kh7"},{"idMove":31,"dsMovement":"Ne5 Rc3"},{"idMove":32,"dsMovement":"Rb1 Rxa3"},{"idMove":33,"dsMovement":"Qb7 Bxe5"},{"idMove":34,"dsMovement":"Qxd5 Bxd5"},{"idMove":35,"dsMovement":"Rxe5 Be6"},{"idMove":36,"dsMovement":"d5 Ra5"},{"idMove":37,"dsMovement":"Rd1 Kg7"},{"idMove":38,"dsMovement":"Rxe6"}]}