{"idGame":365889,"result":"1-0","nmEvent":"Manila ol (Men)","nmSite":"Manila","date":"1992.??.??","round":"?","nmWhitePlayer":"Panno, Oscar","nmBlackPlayer":"Hoi, Carsten","vlWhiteElo":"2465","vlBlackElo":"2430","cdEco":"B07","moves":[{"idMove":0,"dsMovement":"d4 g6"},{"idMove":1,"dsMovement":"e4 Bg7"},{"idMove":2,"dsMovement":"Nc3 d6"},{"idMove":3,"dsMovement":"g3 Nf6"},{"idMove":4,"dsMovement":"Bg2 O-O"},{"idMove":5,"dsMovement":"Nge2 e5"},{"idMove":6,"dsMovement":"h3 Nc6"},{"idMove":7,"dsMovement":"Be3 Bd7"},{"idMove":8,"dsMovement":"O-O Re8"},{"idMove":9,"dsMovement":"Re1 Qc8"},{"idMove":10,"dsMovement":"Kh2 exd4"},{"idMove":11,"dsMovement":"Nxd4 Re5"},{"idMove":12,"dsMovement":"Nf3 Rh5"},{"idMove":13,"dsMovement":"Nh4 Ne5"},{"idMove":14,"dsMovement":"f4 Nc4"},{"idMove":15,"dsMovement":"Bc1 Qd8"},{"idMove":16,"dsMovement":"Rf1 Rxh4"},{"idMove":17,"dsMovement":"gxh4 Nh5"},{"idMove":18,"dsMovement":"Qe1 Bf6"},{"idMove":19,"dsMovement":"Rf3 b5"},{"idMove":20,"dsMovement":"a4 bxa4"},{"idMove":21,"dsMovement":"Nd5 Bg7"},{"idMove":22,"dsMovement":"c3 Rb8"},{"idMove":23,"dsMovement":"Qf2 Nb6"},{"idMove":24,"dsMovement":"Rd3 Bb5"},{"idMove":25,"dsMovement":"Rd1 Bc6"},{"idMove":26,"dsMovement":"Bf3 Nf6"},{"idMove":27,"dsMovement":"Nxb6 Rxb6"},{"idMove":28,"dsMovement":"e5 Bxf3"},{"idMove":29,"dsMovement":"Qxf3 Nh5"},{"idMove":30,"dsMovement":"Rxa4 Qxh4"},{"idMove":31,"dsMovement":"exd6 cxd6"},{"idMove":32,"dsMovement":"Ra1 h6"},{"idMove":33,"dsMovement":"Rf1 Nf6"},{"idMove":34,"dsMovement":"Kg2 d5"},{"idMove":35,"dsMovement":"Qf2 Qxf2"},{"idMove":36,"dsMovement":"Rxf2 Ne4"},{"idMove":37,"dsMovement":"Re2 f5"},{"idMove":38,"dsMovement":"Rxa7 Rb5"},{"idMove":39,"dsMovement":"Re1 Nf6"},{"idMove":40,"dsMovement":"Ra6 Kf7"},{"idMove":41,"dsMovement":"Ree6 Rb8"},{"idMove":42,"dsMovement":"Rab6 Ra8"},{"idMove":43,"dsMovement":"Ra6 Rb8"},{"idMove":44,"dsMovement":"Reb6 Re8"},{"idMove":45,"dsMovement":"Rb7 Kg8"},{"idMove":46,"dsMovement":"Kf3 d4"},{"idMove":47,"dsMovement":"cxd4 Re1"},{"idMove":48,"dsMovement":"Ra8 Kh7"},{"idMove":49,"dsMovement":"Bd2 Rh1"},{"idMove":50,"dsMovement":"Raa7 Nh5"},{"idMove":51,"dsMovement":"d5 Rxh3"},{"idMove":52,"dsMovement":"Kg2 Rd3"},{"idMove":53,"dsMovement":"Bc3 g5"},{"idMove":54,"dsMovement":"Rxg7"}]}