{"idGame":38736,"result":"0-1","nmEvent":"San Francisco sim","nmSite":"San Francisco","date":"1929.??.??","round":"?","nmWhitePlayer":"Alekhine, Alexander","nmBlackPlayer":"Vedensky, D.","vlWhiteElo":"","vlBlackElo":"","cdEco":"E12","moves":[{"idMove":0,"dsMovement":"d4 Nf6"},{"idMove":1,"dsMovement":"Nf3 e6"},{"idMove":2,"dsMovement":"c4 b6"},{"idMove":3,"dsMovement":"Bg5 Bb7"},{"idMove":4,"dsMovement":"Nbd2 Be7"},{"idMove":5,"dsMovement":"Qc2 d6"},{"idMove":6,"dsMovement":"e3 Nbd7"},{"idMove":7,"dsMovement":"Bd3 O-O"},{"idMove":8,"dsMovement":"h4 c5"},{"idMove":9,"dsMovement":"Rd1 d5"},{"idMove":10,"dsMovement":"Ne5 h6"},{"idMove":11,"dsMovement":"f4 Nxe5"},{"idMove":12,"dsMovement":"fxe5 Ng4"},{"idMove":13,"dsMovement":"Bxe7 Qxe7"},{"idMove":14,"dsMovement":"Nf1 f5"},{"idMove":15,"dsMovement":"Be2 dxc4"},{"idMove":16,"dsMovement":"Bxc4 cxd4"},{"idMove":17,"dsMovement":"exd4 Rac8"},{"idMove":18,"dsMovement":"Qb3 Rxc4"},{"idMove":19,"dsMovement":"Qxc4 Bxg2"},{"idMove":20,"dsMovement":"Rg1 Qxh4"},{"idMove":21,"dsMovement":"Kd2 Qf2"},{"idMove":22,"dsMovement":"Kc1 Bd5"}]}