{"idGame":73538,"result":"1-0","nmEvent":"WCh","nmSite":"Brissago SUI","date":"2004.10.02","round":"5","nmWhitePlayer":"Leko,P","nmBlackPlayer":"Kramnik,V","vlWhiteElo":"2741","vlBlackElo":"2770","cdEco":"D37","moves":[{"idMove":0,"dsMovement":"d4 Nf6"},{"idMove":1,"dsMovement":"c4 e6"},{"idMove":2,"dsMovement":"Nf3 d5"},{"idMove":3,"dsMovement":"Nc3 Be7"},{"idMove":4,"dsMovement":"Bf4 O-O"},{"idMove":5,"dsMovement":"e3 c5"},{"idMove":6,"dsMovement":"dxc5 Bxc5"},{"idMove":7,"dsMovement":"cxd5 Nxd5"},{"idMove":8,"dsMovement":"Nxd5 exd5"},{"idMove":9,"dsMovement":"a3 Nc6"},{"idMove":10,"dsMovement":"Bd3 Bb6"},{"idMove":11,"dsMovement":"O-O Bg4"},{"idMove":12,"dsMovement":"h3 Bh5"},{"idMove":13,"dsMovement":"b4 Re8"},{"idMove":14,"dsMovement":"Rc1 a6"},{"idMove":15,"dsMovement":"Bxa6 Rxa6"},{"idMove":16,"dsMovement":"b5 Rxa3"},{"idMove":17,"dsMovement":"bxc6 bxc6"},{"idMove":18,"dsMovement":"Rxc6 Ra7"},{"idMove":19,"dsMovement":"Rd6 Rd7"},{"idMove":20,"dsMovement":"Qxd5 Rxd6"},{"idMove":21,"dsMovement":"Qxd6 Qxd6"},{"idMove":22,"dsMovement":"Bxd6 Bxf3"},{"idMove":23,"dsMovement":"gxf3 Bd8"},{"idMove":24,"dsMovement":"Rb1 Bf6"},{"idMove":25,"dsMovement":"Kg2 g6"},{"idMove":26,"dsMovement":"f4 Kg7"},{"idMove":27,"dsMovement":"Rb7 Re6"},{"idMove":28,"dsMovement":"Rd7 Re8"},{"idMove":29,"dsMovement":"Ra7 Re6"},{"idMove":30,"dsMovement":"Bc5 Rc6"},{"idMove":31,"dsMovement":"Ra5 Bc3"},{"idMove":32,"dsMovement":"Rb5 Ra6"},{"idMove":33,"dsMovement":"Rb3 Bf6"},{"idMove":34,"dsMovement":"Rb8 h5"},{"idMove":35,"dsMovement":"Rb5 Bc3"},{"idMove":36,"dsMovement":"Rb3 Bf6"},{"idMove":37,"dsMovement":"e4 Ra5"},{"idMove":38,"dsMovement":"Be3 Ra4"},{"idMove":39,"dsMovement":"e5 Be7"},{"idMove":40,"dsMovement":"Rb7 Kf8"},{"idMove":41,"dsMovement":"Rb8 Kg7"},{"idMove":42,"dsMovement":"Kf3 Rc4"},{"idMove":43,"dsMovement":"Ke2 Ra4"},{"idMove":44,"dsMovement":"Kd3 Bh4"},{"idMove":45,"dsMovement":"Bd4 Ra3"},{"idMove":46,"dsMovement":"Kc2 Ra2"},{"idMove":47,"dsMovement":"Kd3 Ra3"},{"idMove":48,"dsMovement":"Kc4 Ra4"},{"idMove":49,"dsMovement":"Kd5 Ra5"},{"idMove":50,"dsMovement":"Kc6 Ra4"},{"idMove":51,"dsMovement":"Kc5 Be7"},{"idMove":52,"dsMovement":"Kd5 Ra5"},{"idMove":53,"dsMovement":"Ke4 Ra4"},{"idMove":54,"dsMovement":"Rc8 Bh4"},{"idMove":55,"dsMovement":"e6 Bf6"},{"idMove":56,"dsMovement":"e7 Rxd4"},{"idMove":57,"dsMovement":"Ke3 Bxe7"},{"idMove":58,"dsMovement":"Kxd4 Bh4"},{"idMove":59,"dsMovement":"f3 f5"},{"idMove":60,"dsMovement":"Rc7 Kf6"},{"idMove":61,"dsMovement":"Kd5 Bg3"},{"idMove":62,"dsMovement":"Rc6 Kg7"},{"idMove":63,"dsMovement":"Ke5 h4"},{"idMove":64,"dsMovement":"Rc7 Kh6"},{"idMove":65,"dsMovement":"Rc4 Kg7"},{"idMove":66,"dsMovement":"Ke6 Bh2"},{"idMove":67,"dsMovement":"Rc7 Kh6"},{"idMove":68,"dsMovement":"Kf7"}]}